setup.py
distributions/Binomialdistribution.py
distributions/Gaussiandistribution.py
distributions/Generaldistribution.py
distributions/__init__.py
kobbra_kai_test.egg-info/PKG-INFO
kobbra_kai_test.egg-info/SOURCES.txt
kobbra_kai_test.egg-info/dependency_links.txt
kobbra_kai_test.egg-info/not-zip-safe
kobbra_kai_test.egg-info/top_level.txt